aiobcrypt/__init__.py
aiobcrypt/py.typed
aiobcrypt-3.2.0.post1.dist-info/LICENSE
aiobcrypt-3.2.0.post1.dist-info/METADATA
aiobcrypt-3.2.0.post1.dist-info/WHEEL
aiobcrypt-3.2.0.post1.dist-info/top_level.txt
aiobcrypt-3.2.0.post1.dist-info/RECORD
